[
  {
    "docID": "N240 Pakulska",
    "et": "AneurysmClip",
    "off": 8105,
    "sff": "aneurysm clip"
  },
  {
    "docID": "N240 Pakulska",
    "et": "MildInjury",
    "off": 32805,
    "sff": "mild injury"
  },
  {
    "docID": "N240 Pakulska",
    "et": "VertebralArea",
    "off": 23434,
    "sff": "and"
  },
  {
    "docID": "N240 Pakulska",
    "et": "Compression",
    "off": 29191,
    "sff": "impact-compression"
  },
  {
    "docID": "N240 Pakulska",
    "et": "Isoflurane",
    "off": 7966,
    "sff": "isoflurane"
  },
  {
    "docID": "N240 Pakulska",
    "et": "Injury",
    "off": 10666,
    "sff": "heat"
  },
  {
    "docID": "N240 Pakulska",
    "et": "Isoflurane",
    "off": 9737,
    "sff": "isoflurane"
  },
  {
    "docID": "N240 Pakulska",
    "et": "Injury",
    "off": 8668,
    "sff": "heat"
  },
  {
    "docID": "N240 Pakulska",
    "et": "T10",
    "off": 31638,
    "sff": "T10"
  }
]
