[
  {
    "docID": "N043 Massey 2008 17540369",
    "et": "Xylazine",
    "off": 7976,
    "sff": "xylazine"
  },
  {
    "docID": "N043 Massey 2008 17540369",
    "et": "Isoflurane",
    "off": 15316,
    "sff": "isoflurane"
  },
  {
    "docID": "N043 Massey 2008 17540369",
    "et": "VertebralArea",
    "off": 15375,
    "sff": "thoracic"
  },
  {
    "docID": "N043 Massey 2008 17540369",
    "et": "IntramuscularLocation",
    "off": 7900,
    "sff": "intramuscular"
  },
  {
    "docID": "N043 Massey 2008 17540369",
    "et": "PartialTransection",
    "off": 9109,
    "sff": "transverse lesion"
  },
  {
    "docID": "N043 Massey 2008 17540369",
    "et": "VertebralArea",
    "off": 9139,
    "sff": "C3 and C4"
  },
  {
    "docID": "N043 Massey 2008 17540369",
    "et": "VertebralArea",
    "off": 9026,
    "sff": "C3 and C4"
  },
  {
    "docID": "N043 Massey 2008 17540369",
    "et": "Vibraknife",
    "off": 9179,
    "sff": "Vibraknife"
  },
  {
    "docID": "N043 Massey 2008 17540369",
    "et": "DosageExtracorporal",
    "off": 7986,
    "sff": "6.5 mg/kg"
  },
  {
    "docID": "N043 Massey 2008 17540369",
    "et": "KetamineAsAnaesthetic",
    "off": 7940,
    "sff": "ketamine hydrochloride"
  }
]
